panoptes/utils/__init__.py
panoptes/utils/error.py
panoptes/utils/horizon.py
panoptes/utils/library.py
panoptes/utils/rs232.py
panoptes/utils/serializers.py
panoptes/utils/time.py
panoptes/utils/utils.py
panoptes/utils/cli/image.py
panoptes/utils/cli/main.py
panoptes/utils/config/__init__.py
panoptes/utils/config/cli.py
panoptes/utils/config/client.py
panoptes/utils/config/helpers.py
panoptes/utils/config/server.py
panoptes/utils/database/__init__.py
panoptes/utils/database/base.py
panoptes/utils/database/file.py
panoptes/utils/database/memory.py
panoptes/utils/images/__init__.py
panoptes/utils/images/bayer.py
panoptes/utils/images/cr2.py
panoptes/utils/images/fits.py
panoptes/utils/images/focus.py
panoptes/utils/images/misc.py
panoptes/utils/images/plot.py
panoptes/utils/serial/__init__.py
panoptes/utils/serial/device.py
panoptes_utils-0.2.53.dist-info/METADATA
panoptes_utils-0.2.53.dist-info/WHEEL
panoptes_utils-0.2.53.dist-info/entry_points.txt
panoptes_utils-0.2.53.dist-info/licenses/AUTHORS.md
panoptes_utils-0.2.53.dist-info/licenses/LICENSE.txt
panoptes_utils-0.2.53.dist-info/RECORD
