Metadata-Version: 2.4
Name: panoptes-utils
Version: 0.2.53
Summary: Astronomical utilities for PANOPTES
Project-URL: Homepage, https://github.com/panoptes/panoptes-utils
Project-URL: Documentation, https://panoptes-utils.readthedocs.io
Project-URL: POCS Documentation, https://pocs.readthedocs.io
Project-URL: Project PANOPTES, https://www.projectpanoptes.org
Project-URL: Forum, https://forum.projectpanoptes.org
Author-email: PANOPTES Team <developers@projectpanoptes.org>
License: The MIT License (MIT)
License-File: AUTHORS.md
License-File: LICENSE.txt
Keywords: PANOPTES,astronomy,physics
Classifier: Development Status :: 4 - Beta
Classifier: Environment :: Console
Classifier: Intended Audience :: Science/Research
Classifier: License :: OSI Approved :: MIT License
Classifier: Operating System :: POSIX
Classifier: Programming Language :: Python :: 3
Classifier: Programming Language :: Python :: 3 :: Only
Classifier: Programming Language :: Python :: 3.12
Classifier: Topic :: Scientific/Engineering :: Astronomy
Classifier: Topic :: Scientific/Engineering :: Physics
Requires-Python: >=3.12
Requires-Dist: astropy
Requires-Dist: click-spinner
Requires-Dist: click<8.3
Requires-Dist: deprecated
Requires-Dist: loguru
Requires-Dist: numpy>=2
Requires-Dist: pyserial>=3.4
Requires-Dist: pytest-loguru
Requires-Dist: python-dateutil
Requires-Dist: requests
Requires-Dist: ruamel-yaml
Requires-Dist: typer
Provides-Extra: config
Requires-Dist: flask; extra == 'config'
Requires-Dist: gevent; extra == 'config'
Requires-Dist: pyyaml; extra == 'config'
Requires-Dist: requests; extra == 'config'
Requires-Dist: scalpl; extra == 'config'
Provides-Extra: docs
Requires-Dist: myst-parser; extra == 'docs'
Requires-Dist: piccolo-theme; extra == 'docs'
Requires-Dist: pytest-mpl; extra == 'docs'
Requires-Dist: sphinx; extra == 'docs'
Provides-Extra: examples
Requires-Dist: matplotlib; extra == 'examples'
Requires-Dist: pandas; extra == 'examples'
Requires-Dist: seaborn; extra == 'examples'
Requires-Dist: streamz; extra == 'examples'
Provides-Extra: images
Requires-Dist: matplotlib; extra == 'images'
Requires-Dist: photutils; extra == 'images'
Requires-Dist: pillow>=9.1.1; extra == 'images'
Requires-Dist: scipy; extra == 'images'
Requires-Dist: sep; extra == 'images'
Requires-Dist: watchfiles; extra == 'images'
Provides-Extra: testing
Requires-Dist: coverage; extra == 'testing'
Requires-Dist: pycodestyle; extra == 'testing'
Requires-Dist: pytest; extra == 'testing'
Requires-Dist: pytest-cov; extra == 'testing'
Requires-Dist: pytest-doctestplus; extra == 'testing'
Requires-Dist: pytest-mpl; extra == 'testing'
Requires-Dist: pytest-remotedata>=0.3.1; extra == 'testing'
Requires-Dist: python-dotenv; extra == 'testing'
Requires-Dist: tox; extra == 'testing'
